{"name": "Rajče tyčkové San Marzano", "cat": "Rajčata", "r1": "Stanoviště: Slunné, chráněné | Zálivka: Pravidelná", "r2": "Spon: 80x60 cm | Výška: 180 cm", "r3": "Plod: Červený, podlouhlý | Hmotnost: 110 g", "r4": "Použití: Omáčky, sušení | Tip: Má málo semen", "shu": "", "raw_ai": "PŘESNÝ NÁZEV: Rajče tyčkové San Marzano 3\nŘ1: Stanoviště: Slunné, chráněné | Zálivka: Pravidelná\nŘ2: Spon: 80x60 cm | Výška: 180 cm\nŘ3: Plod: Červený, podlouhlý | Hmotnost: 110 g\nŘ4: Použití: Omáčky, sušení | Tip: Má málo semen\n"}